eexp_engine_utils/__init__.py
eexp_engine_utils/controller.py
eexp_engine_utils/exceptions.py
eexp_engine_utils/validation.py
eexp_engine_utils/utilities/kubeflow_utils.py
eexp_engine_utils/utilities/local_utils.py
eexp_engine_utils/utilities/proactive_utils.py
eexp_engine_utils-1.0.3.dist-info/licenses/LICENCE
eexp_engine_utils-1.0.3.dist-info/METADATA
eexp_engine_utils-1.0.3.dist-info/WHEEL
eexp_engine_utils-1.0.3.dist-info/top_level.txt
eexp_engine_utils-1.0.3.dist-info/RECORD
