Metadata-Version: 2.4
Name: eexp_engine_utils
Version: 1.0.3
Summary: Helper utilities for eexp_engine - supporting ProActive and Kubeflow execution environments
Author-email: "Ilias Gerostathopoulos, Konstantinos Kozanis" <iliasger@gmail.com>
Project-URL: Homepage, https://github.com/extremexp-HORIZON/extremexp-experimentation-engine
Project-URL: Issues, https://github.com/extremexp-HORIZON/extremexp-experimentation-engine/issues
Classifier: Programming Language :: Python :: 3
Classifier: License :: OSI Approved :: Apache Software License
Classifier: Operating System :: OS Independent
Requires-Python: >=3.8
License-File: LICENCE
Requires-Dist: requests==2.32.5
Requires-Dist: fsspec==2025.10.0
Requires-Dist: s3fs==2025.10.0
Requires-Dist: minio==7.2.18
Requires-Dist: pandas==2.2.0
Requires-Dist: numpy==1.26.4
Dynamic: license-file
